Workbook

Sheet START HERE
A1: Share Tracker - read this first
A2: Not financial advice. Built by an AI assistant, not a licensed financial adviser.
A4: COLOURS
A5: Yellow cells = you type here. Green cells = calculated automatically - don't type over them.
A7: THE 5 SHEETS YOU USE
A8: 1. Settings - fill in once (your names, brokerage cost, target mix). Change only after a planned review.
A9: 2. Pre-Buy Gate - fill in BEFORE every buy or sell. If the result says STOP, you don't place the order.
A10: 3. Transactions - one row for every buy or sell, copied from your broker's confirmation email.
A11: 4. Dividends - one row for every dividend/distribution paid (they arrive in your bank account or as extra units).
A12: 5. Prices - once a month (e.g. first Sunday), type today's price for each fund you own.
A14: THE 2 SHEETS YOU READ
A15: Holdings - what you own, what it cost, what it's worth, and whether your mix has drifted from target.
... A39: The Dividends sheet totals cash + franking credits per financial year as a cross-check.

Sheet Dashboard
A1: Dashboard
A2: Read-only. Judge the PROCESS, not this month's price.
A4: MONEY
A5: Total cash put in (buys incl. brokerage) | B5: =-SUMIF(Transactions!$C$5:$C$504,"Buy",Transactions!$G$5:$G$504)
A6: Total cash taken out (sells after brokerage) | B6: =SUMIF(Transactions!$C$5:$C$504,"Sell",Transactions!$G$5:$G$504)
A7: Current market value | B7: =Holdings!F16 | C7: Only as fresh as your last Prices update.
A8: Dividends received (cash) | B8: =SUM(Dividends!$C$5:$C$504) | C8: Includes reinvested amounts.
A9: Franking credits earned | B9: =SUM(Dividends!$E$5:$E$504) | C9: A tax credit, claimed at tax time. Can be refunded if your tax is low.
A10: Total gain (value + money out + dividends - money in) | B10: =B7+B6+B8-B5 | C10: Includes dividends, so this is your true total return in dollars.
A11: Total gain % on money put in | B11: =IF(B5=0,"",B10/B5)
A13: PROCESS SCORECARD (this is what you grade yourself on)
A14: Total brokerage paid | B14: =SUM(Transactions!$F$5:$F$504)
A15: Brokerage as % of all money invested | B15: =IF(B5=0,"",B14/B5) | C15: Target: under 0.5% overall. Above 1% = trading too often in small amounts.
A16: Number of trades | B16: =COUNTIF(Transactions!$C$5:$C$504,"Buy")+COUNTIF(Transactions!$C$5:$C$504,"Sell")
A17: Trades that did NOT pass the Gate | B17: =COUNTIF(Transactions!$I$5:$I$504,"N") | C17: Target: 0. Every one of these is a process failure even if it made money.
A18: Sells | B18: =COUNTIF(Transactions!$C$5:$C$504,"Sell") | C18: In Years 1-3 this should be 0 or 1 (rebalance only).
A19: Largest drift from target mix | B19: =MAX(MAX(Holdings!K5:K14),-MIN(Holdings!K5:K14)) | C19: Under 5% is fine.
A21: REALITY CHECK - what 'income' this produces
A22: Value x 3.5% (rough yearly distribution estimate) | B22: =B7*0.035 | C22: ASX 200 cash yield has recently been ~3.3-3.5%. Diversified ETFs often lower. An estimate, not a promise.
A23: Per week | B23: =B22/52 | C23: This is why contributions matter far more than picking.
A26: Reinvested dividends (DRP): enter the payment in Dividends AND the new units in Transactions as a Buy with brokerage 0 and price = cash / units. The gain line stays correct; 'Total cash put in' will then include reinvested money as well as your own deposits.

Sheet Settings
A1: Settings
A2: Fill in once. Yellow cells only.
A4: Account holder name(s) | C4: As shown on the broker account.
A5: Broker | C5: e.g. CMC Invest / Vanguard Personal Investor / Betashares Direct.
A6: Start date | C6: Date of your first deposit (DD/MM/YYYY).
A7: Typical brokerage per trade ($) | B7: 0 | C7: From your broker's pricing page. Used by the Gate.
A8: Max brokerage as % of an order | B8: 0.01 | C8: 1% rule. Don't change this unless you know why.
A9: Planned monthly contribution ($) | B9: 0 | C9: What you can add each month without touching emergency money.
A10: Emergency fund held in savings ($) | B10: 0 | C10: Cash you can reach in 1 day. Aim for 3-6 months of expenses.
A11: Marginal tax rate of account holder | B11: 0.16 | C11: Used for rough after-tax estimates only. Check your own bracket.
A12: Benchmark fund ticker | B12: VDHG | C12: The single fund you compare yourself against (see Dashboard).
A14: TARGET MIX (must add up to 100%)
A15: Ticker (ASX code) | B15: Target % | C15: What it is
A16: VDHG | B16: 1 | C16: Example only - one diversified fund. Replace with your chosen fund(s).
A26: Total (must be 100%) | B26: =SUM(B16:B25)

Sheet Pre-Buy Gate
A1: Pre-Buy Gate
A2: Fill in before EVERY order. Answer honestly. If any line fails, the answer is STOP.
A4: Check | B4: Your answer | C4: Pass? | D4: Why it matters
A5: Order: Buy or Sell? | D5: Sells need an extra reason - see row 13.
A6: Ticker (ASX code) | D6: Must be on your Target Mix list in Settings.
A7: Order size ($, before brokerage)
A8: Is the ticker in my Target Mix? | B8: =IF(B6="","",IF(COUNTIF(Settings!A16:A25,B6)>0,"Yes","No")) | C8: =IF(B8="","",IF(B8="Yes","PASS","FAIL")) | D8: No new ideas mid-stream. Change the plan at a review, not on impulse.
A9: Brokerage as % of the order | B9: =IF(N(B7)=0,"",Settings!B7/B7) | C9: =IF(B9="","",IF(B9<=Settings!B8,"PASS","FAIL")) | D9: Above 1%, fees eat the return. Save up and buy less often instead.
A10: Emergency fund in place? (Y/N) | C10: =IF(B10="","",IF(UPPER(B10)="Y","PASS","FAIL")) | D10: Never invest money you might need next year.
A11: Will I leave this money for 5+ years? (Y/N) | C11: =IF(B11="","",IF(UPPER(B11)="Y","PASS","FAIL")) | D11: Shares can fall 30%+ and take years to recover.
A12: Is this part of my monthly routine or yearly rebalance? (Y/N) | C12: =IF(B12="","",IF(UPPER(B12)="Y","PASS","FAIL")) | D12: Unplanned trades are where beginners lose money.
A13: If SELLING: is it for rebalancing or a planned need, NOT because prices fell? (Y/N/NA) | C13: =IF(B13="","",IF(OR(UPPER(B13)="Y",AND(UPPER(B13)="NA",UPPER(B5)="BUY")),"PASS","FAIL")) | D13: Panic selling is the #1 wealth destroyer.
A14: Did a tip, forum, ad or news story prompt this? (Y/N) | C14: =IF(B14="","",IF(UPPER(B14)="N","PASS","FAIL")) | D14: If yes, wait 7 days and come back.
A16: GATE RESULT | B16: =IF(COUNTBLANK(B5:B14)>0,"Fill in every yellow cell",IF(COUNTIF(C8:C14,"FAIL")>0,"STOP - do not place this order","GO - place order, then log it"))
A18: After each order, clear the yellow cells (select them, press Delete) so it's fresh next time.

Sheet Transactions
A1: Transactions
A2: One row per buy or sell. Copy figures from the broker's trade confirmation.
A4: Date | B4: Ticker | C4: Buy/Sell | D4: Units | E4: Price per unit ($) | F4: Brokerage ($) | G4: Cash out(-) / in(+) ($) | H4: Brokerage % of order | I4: Gate passed? (Y/N) | J4: Notes / reason
G5: =IF(OR(C5="",D5=""),"",IF(C5="Buy",-(D5*E5+F5),D5*E5-F5)) | H5: =IF(OR(D5="",E5="",D5*E5=0),"",F5/(D5*E5))
G6: =IF(OR(C6="",D6=""),"",IF(C6="Buy",-(D6*E6+F6),D6*E6-F6)) | H6: =IF(OR(D6="",E6="",D6*E6=0),"",F6/(D6*E6))
G7: =IF(OR(C7="",D7=""),"",IF(C7="Buy",-(D7*E7+F7),D7*E7-F7)) | H7: =IF(OR(D7="",E7="",D7*E7=0),"",F7/(D7*E7))
G8: =IF(OR(C8="",D8=""),"",IF(C8="Buy",-(D8*E8+F8),D8*E8-F8)) | H8: =IF(OR(D8="",E8="",D8*E8=0),"",F8/(D8*E8))
G9: =IF(OR(C9="",D9=""),"",IF(C9="Buy",-(D9*E9+F9),D9*E9-F9)) | H9: =IF(OR(D9="",E9="",D9*E9=0),"",F9/(D9*E9))
G10: =IF(OR(C10="",D10=""),"",IF(C10="Buy",-(D10*E10+F10),D10*E10-F10)) | H10: =IF(OR(D10="",E10="",D10*E10=0),"",F10/(D10*E10))
G11: =IF(OR(C11="",D11=""),"",IF(C11="Buy",-(D11*E11+F11),D11*E11-F11)) | H11: =IF(OR(D11="",E11="",D11*E11=0),"",F11/(D11*E11))
G12: =IF(OR(C12="",D12=""),"",IF(C12="Buy",-(D12*E12+F12),D12*E12-F12)) | H12: =IF(OR(D12="",E12="",D12*E12=0),"",F12/(D12*E12))
G13: =IF(OR(C13="",D13=""),"",IF(C13="Buy",-(D13*E13+F13),D13*E13-F13)) | H13: =IF(OR(D13="",E13="",D13*E13=0),"",F13/(D13*E13))
G14: =IF(OR(C14="",D14=""),"",IF(C14="Buy",-(D14*E14+F14),D14*E14-F14)) | H14: =IF(OR(D14="",E14="",D14*E14=0),"",F14/(D14*E14))
G15: =IF(OR(C15="",D15=""),"",IF(C15="Buy",-(D15*E15+F15),D15*E15-F15)) | H15: =IF(OR(D15="",E15="",D15*E15=0),"",F15/(D15*E15))
G16: =IF(OR(C16="",D16=""),"",IF(C16="Buy",-(D16*E16+F16),D16*E16-F16)) | H16: =IF(OR(D16="",E16="",D16*E16=0),"",F16/(D16*E16))
... G504: =IF(OR(C504="",D504=""),"",IF(C504="Buy",-(D504*E504+F504),D504*E504-F504)) | H504: =IF(OR(D504="",E504="",D504*E504=0),"",F504/(D504*E504))

Sheet Dividends
A1: Dividends & Distributions
A2: One row per payment. Franking % is on the distribution statement (ETFs often 0-80%).
A4: Pay date | B4: Ticker | C4: Cash received ($) | D4: Franked % (0-100%) | E4: Franking credit ($) | F4: Reinvested? (Y/N) | G4: Units received if reinvested | H4: Financial year | I4: Notes
E5: =IF(C5="","",C5*N(D5)*30/70) | H5: =IF(A5="","","FY"&(YEAR(A5)+IF(MONTH(A5)>=7,1,0)))
E6: =IF(C6="","",C6*N(D6)*30/70) | H6: =IF(A6="","","FY"&(YEAR(A6)+IF(MONTH(A6)>=7,1,0)))
E7: =IF(C7="","",C7*N(D7)*30/70) | H7: =IF(A7="","","FY"&(YEAR(A7)+IF(MONTH(A7)>=7,1,0)))
E8: =IF(C8="","",C8*N(D8)*30/70) | H8: =IF(A8="","","FY"&(YEAR(A8)+IF(MONTH(A8)>=7,1,0)))
E9: =IF(C9="","",C9*N(D9)*30/70) | H9: =IF(A9="","","FY"&(YEAR(A9)+IF(MONTH(A9)>=7,1,0)))
E10: =IF(C10="","",C10*N(D10)*30/70) | H10: =IF(A10="","","FY"&(YEAR(A10)+IF(MONTH(A10)>=7,1,0)))
E11: =IF(C11="","",C11*N(D11)*30/70) | H11: =IF(A11="","","FY"&(YEAR(A11)+IF(MONTH(A11)>=7,1,0)))
E12: =IF(C12="","",C12*N(D12)*30/70) | H12: =IF(A12="","","FY"&(YEAR(A12)+IF(MONTH(A12)>=7,1,0)))
E13: =IF(C13="","",C13*N(D13)*30/70) | H13: =IF(A13="","","FY"&(YEAR(A13)+IF(MONTH(A13)>=7,1,0)))
E14: =IF(C14="","",C14*N(D14)*30/70) | H14: =IF(A14="","","FY"&(YEAR(A14)+IF(MONTH(A14)>=7,1,0)))
E15: =IF(C15="","",C15*N(D15)*30/70) | H15: =IF(A15="","","FY"&(YEAR(A15)+IF(MONTH(A15)>=7,1,0)))
E16: =IF(C16="","",C16*N(D16)*30/70) | H16: =IF(A16="","","FY"&(YEAR(A16)+IF(MONTH(A16)>=7,1,0)))
... E504: =IF(C504="","",C504*N(D504)*30/70) | H504: =IF(A504="","","FY"&(YEAR(A504)+IF(MONTH(A504)>=7,1,0)))

Sheet Prices
A1: Latest prices
A2: Update monthly. Ticker list should match Settings > Target Mix.
A4: Ticker | B4: Latest price ($) | C4: Price date
A5: VDHG

Sheet Holdings
A1: Holdings
A2: All calculated. Tickers come from Settings > Target Mix.
A4: Ticker | B4: Units held | C4: Total cost incl. brokerage ($) | D4: Average cost / unit ($) | E4: Latest price ($) | F4: Market value ($) | G4: Gain/loss ($) | H4: Gain/loss % | I4: Actual % of portfolio | J4: Target % | K4: Drift (actual - target)
A5: =IF(Settings!A16="","",Settings!A16) | B5: =IF(A5="","",SUMIFS(Transactions!$D$5:$D$504,Transactions!$B$5:$B$504,A5,Transactions!$C$5:$C$504,"Buy")-SUMIFS(Transactions!$D$5:$D$504,Transactions!$B$5:$B$504,A5,Transactions!$C$5:$C$504,"Sell")) | C5: =IF(A5="","",IF(SUMIFS(Transactions!$D$5:$D$504,Transactions!$B$5:$B$504,A5,Transactions!$C$5:$C$504,"Buy")=0,0,(-SUMIFS(Transactions!$G$5:$G$504,Transactions!$B$5:$B$504,A5,Transactions!$C$5:$C$504,"Buy"))*B5/SUMIFS(Transactions!$D$5:$D$504,Transactions!$B$5:$B$504,A5,Transactions!$C$5:$C$504,"Buy"))) | D5: =IF(OR(A5="",N(B5)=0),"",C5/B5) | E5: =IF(A5="","",IFERROR(VLOOKUP(A5,Prices!$A$5:$B$24,2,FALSE),"")) | F5: =IF(OR(A5="",E5=""),"",B5*E5) | G5: =IF(F5="","",F5-C5) | H5: =IF(OR(G5="",N(C5)=0),"",G5/C5) | I5: =IF(OR(F5="",N($F$16)=0),"",F5/$F$16) | J5: =IF(A5="","",Settings!B16) | K5: =IF(I5="","",I5-J5)
A6: =IF(Settings!A17="","",Settings!A17) | B6: =IF(A6="","",SUMIFS(Transactions!$D$5:$D$504,Transactions!$B$5:$B$504,A6,Transactions!$C$5:$C$504,"Buy")-SUMIFS(Transactions!$D$5:$D$504,Transactions!$B$5:$B$504,A6,Transactions!$C$5:$C$504,"Sell")) | C6: =IF(A6="","",IF(SUMIFS(Transactions!$D$5:$D$504,Transactions!$B$5:$B$504,A6,Transactions!$C$5:$C$504,"Buy")=0,0,(-SUMIFS(Transactions!$G$5:$G$504,Transactions!$B$5:$B$504,A6,Transactions!$C$5:$C$504,"Buy"))*B6/SUMIFS(Transactions!$D$5:$D$504,Transactions!$B$5:$B$504,A6,Transactions!$C$5:$C$504,"Buy"))) | D6: =IF(OR(A6="",N(B6)=0),"",C6/B6) | E6: =IF(A6="","",IFERROR(VLOOKUP(A6,Prices!$A$5:$B$24,2,FALSE),"")) | F6: =IF(OR(A6="",E6=""),"",B6*E6) | G6: =IF(F6="","",F6-C6) | H6: =IF(OR(G6="",N(C6)=0),"",G6/C6) | I6: =IF(OR(F6="",N($F$16)=0),"",F6/$F$16) | J6: =IF(A6="","",Settings!B17) | K6: =IF(I6="","",I6-J6)
A7: =IF(Settings!A18="","",Settings!A18) | B7: =IF(A7="","",SUMIFS(Transactions!$D$5:$D$504,Transactions!$B$5:$B$504,A7,Transactions!$C$5:$C$504,"Buy")-SUMIFS(Transactions!$D$5:$D$504,Transactions!$B$5:$B$504,A7,Transactions!$C$5:$C$504,"Sell")) | C7: =IF(A7="","",IF(SUMIFS(Transactions!$D$5:$D$504,Transactions!$B$5:$B$504,A7,Transactions!$C$5:$C$504,"Buy")=0,0,(-SUMIFS(Transactions!$G$5:$G$504,Transactions!$B$5:$B$504,A7,Transactions!$C$5:$C$504,"Buy"))*B7/SUMIFS(Transactions!$D$5:$D$504,Transactions!$B$5:$B$504,A7,Transactions!$C$5:$C$504,"Buy"))) | D7: =IF(OR(A7="",N(B7)=0),"",C7/B7) | E7: =IF(A7="","",IFERROR(VLOOKUP(A7,Prices!$A$5:$B$24,2,FALSE),"")) | F7: =IF(OR(A7="",E7=""),"",B7*E7) | G7: =IF(F7="","",F7-C7) | H7: =IF(OR(G7="",N(C7)=0),"",G7/C7) | I7: =IF(OR(F7="",N($F$16)=0),"",F7/$F$16) | J7: =IF(A7="","",Settings!B18) | K7: =IF(I7="","",I7-J7)
A8: =IF(Settings!A19="","",Settings!A19) | B8: =IF(A8="","",SUMIFS(Transactions!$D$5:$D$504,Transactions!$B$5:$B$504,A8,Transactions!$C$5:$C$504,"Buy")-SUMIFS(Transactions!$D$5:$D$504,Transactions!$B$5:$B$504,A8,Transactions!$C$5:$C$504,"Sell")) | C8: =IF(A8="","",IF(SUMIFS(Transactions!$D$5:$D$504,Transactions!$B$5:$B$504,A8,Transactions!$C$5:$C$504,"Buy")=0,0,(-SUMIFS(Transactions!$G$5:$G$504,Transactions!$B$5:$B$504,A8,Transactions!$C$5:$C$504,"Buy"))*B8/SUMIFS(Transactions!$D$5:$D$504,Transactions!$B$5:$B$504,A8,Transactions!$C$5:$C$504,"Buy"))) | D8: =IF(OR(A8="",N(B8)=0),"",C8/B8) | E8: =IF(A8="","",IFERROR(VLOOKUP(A8,Prices!$A$5:$B$24,2,FALSE),"")) | F8: =IF(OR(A8="",E8=""),"",B8*E8) | G8: =IF(F8="","",F8-C8) | H8: =IF(OR(G8="",N(C8)=0),"",G8/C8) | I8: =IF(OR(F8="",N($F$16)=0),"",F8/$F$16) | J8: =IF(A8="","",Settings!B19) | K8: =IF(I8="","",I8-J8)
A9: =IF(Settings!A20="","",Settings!A20) | B9: =IF(A9="","",SUMIFS(Transactions!$D$5:$D$504,Transactions!$B$5:$B$504,A9,Transactions!$C$5:$C$504,"Buy")-SUMIFS(Transactions!$D$5:$D$504,Transactions!$B$5:$B$504,A9,Transactions!$C$5:$C$504,"Sell")) | C9: =IF(A9="","",IF(SUMIFS(Transactions!$D$5:$D$504,Transactions!$B$5:$B$504,A9,Transactions!$C$5:$C$504,"Buy")=0,0,(-SUMIFS(Transactions!$G$5:$G$504,Transactions!$B$5:$B$504,A9,Transactions!$C$5:$C$504,"Buy"))*B9/SUMIFS(Transactions!$D$5:$D$504,Transactions!$B$5:$B$504,A9,Transactions!$C$5:$C$504,"Buy"))) | D9: =IF(OR(A9="",N(B9)=0),"",C9/B9) | E9: =IF(A9="","",IFERROR(VLOOKUP(A9,Prices!$A$5:$B$24,2,FALSE),"")) | F9: =IF(OR(A9="",E9=""),"",B9*E9) | G9: =IF(F9="","",F9-C9) | H9: =IF(OR(G9="",N(C9)=0),"",G9/C9) | I9: =IF(OR(F9="",N($F$16)=0),"",F9/$F$16) | J9: =IF(A9="","",Settings!B20) | K9: =IF(I9="","",I9-J9)
A10: =IF(Settings!A21="","",Settings!A21) | B10: =IF(A10="","",SUMIFS(Transactions!$D$5:$D$504,Transactions!$B$5:$B$504,A10,Transactions!$C$5:$C$504,"Buy")-SUMIFS(Transactions!$D$5:$D$504,Transactions!$B$5:$B$504,A10,Transactions!$C$5:$C$504,"Sell")) | C10: =IF(A10="","",IF(SUMIFS(Transactions!$D$5:$D$504,Transactions!$B$5:$B$504,A10,Transactions!$C$5:$C$504,"Buy")=0,0,(-SUMIFS(Transactions!$G$5:$G$504,Transactions!$B$5:$B$504,A10,Transactions!$C$5:$C$504,"Buy"))*B10/SUMIFS(Transactions!$D$5:$D$504,Transactions!$B$5:$B$504,A10,Transactions!$C$5:$C$504,"Buy"))) | D10: =IF(OR(A10="",N(B10)=0),"",C10/B10) | E10: =IF(A10="","",IFERROR(VLOOKUP(A10,Prices!$A$5:$B$24,2,FALSE),"")) | F10: =IF(OR(A10="",E10=""),"",B10*E10) | G10: =IF(F10="","",F10-C10) | H10: =IF(OR(G10="",N(C10)=0),"",G10/C10) | I10: =IF(OR(F10="",N($F$16)=0),"",F10/$F$16) | J10: =IF(A10="","",Settings!B21) | K10: =IF(I10="","",I10-J10)
A11: =IF(Settings!A22="","",Settings!A22) | B11: =IF(A11="","",SUMIFS(Transactions!$D$5:$D$504,Transactions!$B$5:$B$504,A11,Transactions!$C$5:$C$504,"Buy")-SUMIFS(Transactions!$D$5:$D$504,Transactions!$B$5:$B$504,A11,Transactions!$C$5:$C$504,"Sell")) | C11: =IF(A11="","",IF(SUMIFS(Transactions!$D$5:$D$504,Transactions!$B$5:$B$504,A11,Transactions!$C$5:$C$504,"Buy")=0,0,(-SUMIFS(Transactions!$G$5:$G$504,Transactions!$B$5:$B$504,A11,Transactions!$C$5:$C$504,"Buy"))*B11/SUMIFS(Transactions!$D$5:$D$504,Transactions!$B$5:$B$504,A11,Transactions!$C$5:$C$504,"Buy"))) | D11: =IF(OR(A11="",N(B11)=0),"",C11/B11) | E11: =IF(A11="","",IFERROR(VLOOKUP(A11,Prices!$A$5:$B$24,2,FALSE),"")) | F11: =IF(OR(A11="",E11=""),"",B11*E11) | G11: =IF(F11="","",F11-C11) | H11: =IF(OR(G11="",N(C11)=0),"",G11/C11) | I11: =IF(OR(F11="",N($F$16)=0),"",F11/$F$16) | J11: =IF(A11="","",Settings!B22) | K11: =IF(I11="","",I11-J11)
A12: =IF(Settings!A23="","",Settings!A23) | B12: =IF(A12="","",SUMIFS(Transactions!$D$5:$D$504,Transactions!$B$5:$B$504,A12,Transactions!$C$5:$C$504,"Buy")-SUMIFS(Transactions!$D$5:$D$504,Transactions!$B$5:$B$504,A12,Transactions!$C$5:$C$504,"Sell")) | C12: =IF(A12="","",IF(SUMIFS(Transactions!$D$5:$D$504,Transactions!$B$5:$B$504,A12,Transactions!$C$5:$C$504,"Buy")=0,0,(-SUMIFS(Transactions!$G$5:$G$504,Transactions!$B$5:$B$504,A12,Transactions!$C$5:$C$504,"Buy"))*B12/SUMIFS(Transactions!$D$5:$D$504,Transactions!$B$5:$B$504,A12,Transactions!$C$5:$C$504,"Buy"))) | D12: =IF(OR(A12="",N(B12)=0),"",C12/B12) | E12: =IF(A12="","",IFERROR(VLOOKUP(A12,Prices!$A$5:$B$24,2,FALSE),"")) | F12: =IF(OR(A12="",E12=""),"",B12*E12) | G12: =IF(F12="","",F12-C12) | H12: =IF(OR(G12="",N(C12)=0),"",G12/C12) | I12: =IF(OR(F12="",N($F$16)=0),"",F12/$F$16) | J12: =IF(A12="","",Settings!B23) | K12: =IF(I12="","",I12-J12)
A13: =IF(Settings!A24="","",Settings!A24) | B13: =IF(A13="","",SUMIFS(Transactions!$D$5:$D$504,Transactions!$B$5:$B$504,A13,Transactions!$C$5:$C$504,"Buy")-SUMIFS(Transactions!$D$5:$D$504,Transactions!$B$5:$B$504,A13,Transactions!$C$5:$C$504,"Sell")) | C13: =IF(A13="","",IF(SUMIFS(Transactions!$D$5:$D$504,Transactions!$B$5:$B$504,A13,Transactions!$C$5:$C$504,"Buy")=0,0,(-SUMIFS(Transactions!$G$5:$G$504,Transactions!$B$5:$B$504,A13,Transactions!$C$5:$C$504,"Buy"))*B13/SUMIFS(Transactions!$D$5:$D$504,Transactions!$B$5:$B$504,A13,Transactions!$C$5:$C$504,"Buy"))) | D13: =IF(OR(A13="",N(B13)=0),"",C13/B13) | E13: =IF(A13="","",IFERROR(VLOOKUP(A13,Prices!$A$5:$B$24,2,FALSE),"")) | F13: =IF(OR(A13="",E13=""),"",B13*E13) | G13: =IF(F13="","",F13-C13) | H13: =IF(OR(G13="",N(C13)=0),"",G13/C13) | I13: =IF(OR(F13="",N($F$16)=0),"",F13/$F$16) | J13: =IF(A13="","",Settings!B24) | K13: =IF(I13="","",I13-J13)
A14: =IF(Settings!A25="","",Settings!A25) | B14: =IF(A14="","",SUMIFS(Transactions!$D$5:$D$504,Transactions!$B$5:$B$504,A14,Transactions!$C$5:$C$504,"Buy")-SUMIFS(Transactions!$D$5:$D$504,Transactions!$B$5:$B$504,A14,Transactions!$C$5:$C$504,"Sell")) | C14: =IF(A14="","",IF(SUMIFS(Transactions!$D$5:$D$504,Transactions!$B$5:$B$504,A14,Transactions!$C$5:$C$504,"Buy")=0,0,(-SUMIFS(Transactions!$G$5:$G$504,Transactions!$B$5:$B$504,A14,Transactions!$C$5:$C$504,"Buy"))*B14/SUMIFS(Transactions!$D$5:$D$504,Transactions!$B$5:$B$504,A14,Transactions!$C$5:$C$504,"Buy"))) | D14: =IF(OR(A14="",N(B14)=0),"",C14/B14) | E14: =IF(A14="","",IFERROR(VLOOKUP(A14,Prices!$A$5:$B$24,2,FALSE),"")) | F14: =IF(OR(A14="",E14=""),"",B14*E14) | G14: =IF(F14="","",F14-C14) | H14: =IF(OR(G14="",N(C14)=0),"",G14/C14) | I14: =IF(OR(F14="",N($F$16)=0),"",F14/$F$16) | J14: =IF(A14="","",Settings!B25) | K14: =IF(I14="","",I14-J14)
A16: TOTAL | C16: =SUM(C5:C14) | F16: =SUM(F5:F14) | G16: =F16-C16 | H16: =IF(C16=0,"",G16/C16)
A18: Red drift = more than 5 percentage points off target. Fix it at the yearly rebalance by directing new money to the underweight fund (cheaper than selling).
